build/lib/build/lib/build/lib/build/lib/build/lib/torchbringer/__init__.py
build/lib/build/lib/build/lib/build/lib/build/lib/torchbringer/components/builders.py
build/lib/build/lib/build/lib/build/lib/build/lib/torchbringer/components/epsilon.py
build/lib/build/lib/build/lib/build/lib/build/lib/torchbringer/components/layers.py
build/lib/build/lib/build/lib/build/lib/build/lib/torchbringer/components/replay_memory.py
build/lib/build/lib/build/lib/build/lib/build/lib/torchbringer/examples/breakout_local_dqn.py
build/lib/build/lib/build/lib/build/lib/build/lib/torchbringer/examples/cartpole_flask_dqn.py
build/lib/build/lib/build/lib/build/lib/build/lib/torchbringer/examples/cartpole_grpc_dqn.py
build/lib/build/lib/build/lib/build/lib/build/lib/torchbringer/examples/cartpole_local_dqn.py
build/lib/build/lib/build/lib/build/lib/build/lib/torchbringer/examples/cartpole_socket_dqn.py
build/lib/build/lib/build/lib/build/lib/build/lib/torchbringer/learners/dqn.py
build/lib/build/lib/build/lib/build/lib/build/lib/torchbringer/learners/learner_utils.py
build/lib/build/lib/build/lib/build/lib/build/lib/torchbringer/servers/torchbringer_agent.py
build/lib/build/lib/build/lib/build/lib/build/lib/torchbringer/servers/flask/torchbringer_flask_client.py
build/lib/build/lib/build/lib/build/lib/build/lib/torchbringer/servers/flask/torchbringer_flask_server.py
build/lib/build/lib/build/lib/build/lib/build/lib/torchbringer/servers/grpc/torchbringer_grpc_client.py
build/lib/build/lib/build/lib/build/lib/build/lib/torchbringer/servers/grpc/torchbringer_grpc_server.py
build/lib/build/lib/build/lib/build/lib/build/lib/torchbringer/servers/grpc/torchbringer_pb2.py
build/lib/build/lib/build/lib/build/lib/build/lib/torchbringer/servers/grpc/torchbringer_pb2.pyi
build/lib/build/lib/build/lib/build/lib/build/lib/torchbringer/servers/grpc/torchbringer_pb2_grpc.py
build/lib/build/lib/build/lib/build/lib/build/lib/torchbringer/servers/socket/torchbringer_socket_client.py
torchbringer-0.5.7.dist-info/LICENSE
torchbringer-0.5.7.dist-info/METADATA
torchbringer-0.5.7.dist-info/WHEEL
torchbringer-0.5.7.dist-info/top_level.txt
torchbringer-0.5.7.dist-info/RECORD
