Metadata-Version: 2.1
Name: torchbringer
Version: 0.5.7
Summary: A PyTorch library for deep reinforcement learning 
Home-page: https://github.com/moraguma/TorchBringer
Author: Moraguma
Author-email: g170603@dac.unicamp.br
License: MIT
Classifier: Development Status :: 3 - Alpha
Classifier: Intended Audience :: Science/Research
Classifier: License :: OSI Approved :: MIT License
Classifier: Operating System :: POSIX :: Linux
Classifier: Environment :: GPU :: NVIDIA CUDA
Classifier: Programming Language :: Python
License-File: LICENSE
Requires-Dist: setuptools
Requires-Dist: torch
Requires-Dist: gymnasium
Requires-Dist: aim
Requires-Dist: numpy
Requires-Dist: opencv-python
Requires-Dist: protobuf
Requires-Dist: grpcio
Requires-Dist: flask
